claude_repair/__init__.py
claude_repair/cli.py
claude_repair-0.1.0.dist-info/LICENSE
claude_repair-0.1.0.dist-info/METADATA
claude_repair-0.1.0.dist-info/WHEEL
claude_repair-0.1.0.dist-info/entry_points.txt
claude_repair-0.1.0.dist-info/RECORD
