Metadata-Version: 2.3
Name: claude-repair
Version: 0.1.0
Summary: High-performance CLI tool to find and repair broken Claude conversation sessions
License: Apache-2.0
Keywords: claude,repair,cli,conversation,session,tool-use,anthropic
Author: Chris Mann
Author-email: cmann50@me.com
Requires-Python: >=3.8,<4.0
Classifier: Development Status :: 4 - Beta
Classifier: Environment :: Console
Classifier: Intended Audience :: Developers
Classifier: License :: OSI Approved :: Apache Software License
Classifier: Operating System :: OS Independent
Classifier: Programming Language :: Python :: 3
Classifier: Programming Language :: Python :: 3.8
Classifier: Programming Language :: Python :: 3.9
Classifier: Programming Language :: Python :: 3.10
Classifier: Programming Language :: Python :: 3.11
Classifier: Programming Language :: Python :: 3.12
Classifier: Programming Language :: Python :: 3.13
Classifier: Topic :: Software Development :: Libraries :: Python Modules
Classifier: Topic :: Utilities
Requires-Dist: click (==8.1.7)
Requires-Dist: python-dateutil (>=2.8.0,<3.0.0)
Requires-Dist: rich (>=13.0.0,<14.0.0)
Requires-Dist: typer (==0.9.0)
Project-URL: Bug Tracker, https://github.com/cmann/claude-repair/issues
Project-URL: Documentation, https://github.com/cmann/claude-repair#readme
Project-URL: Homepage, https://github.com/cmann/claude-repair
Project-URL: Repository, https://github.com/cmann/claude-repair
